numpytorch
