Metadata-Version: 2.1
Name: numpytorch
Version: 0.1.1
Summary: Monkey-patched numpy with pytorch syntax
Home-page: https://github.com/ashawkey/numpytorch
Author: kiui
Author-email: ashawkey1999@gmail.com
License: UNKNOWN
Keywords: deep learning,tensor manipulation,machine learning,scientific computations
Platform: UNKNOWN
Classifier: Intended Audience :: Science/Research
Classifier: Programming Language :: Python :: 3 
